README.md
TFANN.py
setup.py
TFANN.egg-info/PKG-INFO
TFANN.egg-info/SOURCES.txt
TFANN.egg-info/dependency_links.txt
TFANN.egg-info/not-zip-safe
TFANN.egg-info/top_level.txt