Metadata-Version: 1.0
Name: TFANN
Version: 1.0.1
Summary: A neural network module containing implementations of MLP, and CNN networks in TensorFlow.
Home-page: http://github.com/nicholastoddsmith/pythonml
Author: Nicholas T. Smith
Author-email: nicholastsmithblog@gmail.com
License: MIT
Keywords: TensorFlow ANN CNN Neural Network
Platform: UNKNOWN
